MANIFEST.in
setup.py
redis_lock/__init__.py
redis_lock.egg-info/PKG-INFO
redis_lock.egg-info/SOURCES.txt
redis_lock.egg-info/dependency_links.txt
redis_lock.egg-info/top_level.txt