Metadata-Version: 1.1
Name: redis-lock
Version: 0.1.0
Summary: A simple pessimistic lock implementation using Redis
Home-page: http://github.com/cezarsa/redis_lock
Author: Cezar Sá Espinola
Author-email: cezarsa@gmail.com
License: MIT
Keywords: redis pessimistic lock setnx
Platform: UNKNOWN
Classifier: Development Status :: 4 - Beta
Classifier: Intended Audience :: Developers
Classifier: Natural Language :: English
Classifier: Operating System :: MacOS
Classifier: Operating System :: POSIX :: Linux
Classifier: Programming Language :: Python :: 2.7
